{"station":"ARRAM","station_name":"Arram","n_services":22,"branches":[{"next_stop":"CTTGHM","next_stop_name":"Cottingham","destination":"Bridlington","destination_tiploc":"BRDLNGT","services":[{"id":"202606207189675","operator":"NT","headcode":"1W36","dep":372,"arr":null,"days":["MF"]},{"id":"202606197189675","operator":"NT","headcode":"1W36","dep":372,"arr":null,"days":["MF"]},{"id":"202606208028644","operator":"NT","headcode":"2W08","dep":462,"arr":null,"days":["MF"]},{"id":"202606198028644","operator":"NT","headcode":"2W08","dep":462,"arr":null,"days":["MF"]},{"id":"202606198024590","operator":"NT","headcode":"2R91","dep":716,"arr":710,"days":["MF"]},{"id":"202606208024590","operator":"NT","headcode":"2R91","dep":716,"arr":710,"days":["MF"]},{"id":"202606208024597","operator":"NT","headcode":"2R95","dep":836,"arr":829,"days":["MF"]},{"id":"202606198024597","operator":"NT","headcode":"2R95","dep":836,"arr":829,"days":["MF"]},{"id":"202606208028678","operator":"NT","headcode":"2W14","dep":1053,"arr":null,"days":["MF"]},{"id":"202606198028678","operator":"NT","headcode":"2W14","dep":1053,"arr":null,"days":["MF"]},{"id":"202606198024488","operator":"NT","headcode":"2R27","dep":1196,"arr":1193,"days":["MF"]},{"id":"202606208024488","operator":"NT","headcode":"2R27","dep":1196,"arr":1193,"days":["MF"]}],"operators":["NT"],"operator_color":"#0072B2","frequency":12},{"next_stop":"BROUGH","next_stop_name":"Brough","destination":"York","destination_tiploc":"YORK","services":[{"id":"202606198024577","operator":"NT","headcode":"2R72","dep":529,"arr":527,"days":["MF"]},{"id":"202606208024578","operator":"NT","headcode":"2R72","dep":529,"arr":526,"days":["MF"]},{"id":"202606198024602","operator":"NT","headcode":"2R98","dep":826,"arr":823,"days":["MF"]},{"id":"202606208024602","operator":"NT","headcode":"2R98","dep":826,"arr":823,"days":["MF"]},{"id":"202606208024583","operator":"NT","headcode":"2R76","dep":1127,"arr":1123,"days":["MF"]},{"id":"202606198024582","operator":"NT","headcode":"2R76","dep":1127,"arr":1123,"days":["MF"]}],"operators":["NT"],"operator_color":"#0072B2","frequency":6},{"next_stop":"HESSLE","next_stop_name":"Hessle","destination":"York","destination_tiploc":"YORK","services":[{"id":"202606198024467","operator":"NT","headcode":"2R20","dep":1067,"arr":1064,"days":["MF"]},{"id":"202606208024467","operator":"NT","headcode":"2R20","dep":1067,"arr":1064,"days":["MF"]}],"operators":["NT"],"operator_color":"#0072B2","frequency":2},{"next_stop":null,"next_stop_name":"Hull","destination":"Hull","destination_tiploc":"HULL","services":[{"id":"202606207189677","operator":"NT","headcode":"1W37","dep":null,"arr":473,"days":["MF"]},{"id":"202606197189677","operator":"NT","headcode":"1W37","dep":null,"arr":473,"days":["MF"]}],"operators":["NT"],"operator_color":"#0072B2","frequency":2}]}