{"station":"ORE","station_name":"Hastings","n_services":208,"branches":[{"next_stop":"OREE","next_stop_name":"Ore","destination":"Ore","destination_tiploc":"OREE","services":[{"id":"202606198727706","operator":"SN","headcode":"2D02","dep":320,"arr":320,"days":["MF"]},{"id":"202606206722255","operator":"SN","headcode":"2D02","dep":320,"arr":null,"days":["MF"]},{"id":"202606207177228","operator":"SN","headcode":"1U90","dep":354,"arr":354,"days":["MF"]},{"id":"202606198732627","operator":"SN","headcode":"2D06","dep":372,"arr":371,"days":["MF"]},{"id":"202606197127020","operator":"SN","headcode":"1U02","dep":377,"arr":376,"days":["MF"]},{"id":"202606207177232","operator":"SN","headcode":"1U92","dep":377,"arr":377,"days":["MF"]},{"id":"202606208727796","operator":"SN","headcode":"2D06","dep":385,"arr":384,"days":["MF"]},{"id":"202606207127056","operator":"SN","headcode":"1U94","dep":414,"arr":414,"days":["MF"]},{"id":"202606197177230","operator":"SN","headcode":"1U92","dep":415,"arr":414,"days":["MF"]},{"id":"202606197127026","operator":"SN","headcode":"1U06","dep":433,"arr":432,"days":["MF"]},{"id":"202606196709816","operator":"SN","headcode":"2D10","dep":439,"arr":438,"days":["MF"]},{"id":"202606208727758","operator":"SN","headcode":"2D10","dep":445,"arr":444,"days":["MF"]},{"id":"202606207127029","operator":"SN","headcode":"1U10","dep":458,"arr":457,"days":["MF"]},{"id":"202606207126377","operator":"SN","headcode":"1F98","dep":481,"arr":480,"days":["MF"]},{"id":"202606197126378","operator":"SN","headcode":"1F98","dep":485,"arr":485,"days":["MF"]},{"id":"202606197177148","operator":"SN","headcode":"1U12","dep":494,"arr":493,"days":["MF"]},{"id":"202606198732625","operator":"SN","headcode":"2D14","dep":505,"arr":505,"days":["MF"]},{"id":"202606208727777","operator":"SN","headcode":"2D14","dep":505,"arr":504,"days":["MF"]},{"id":"202606207127033","operator":"SN","headcode":"1U14","dep":518,"arr":517,"days":["MF"]},{"id":"202606197126276","operator":"SN","headcode":"1F04","dep":535,"arr":535,"days":["MF"]},{"id":"202606207126277","operator":"SN","headcode":"1F04","dep":540,"arr":539,"days":["MF"]},{"id":"202606198732601","operator":"SN","headcode":"2D18","dep":565,"arr":564,"days":["MF"]},{"id":"202606208727801","operator":"SN","headcode":"2D18","dep":565,"arr":564,"days":["MF"]},{"id":"202606207127036","operator":"SN","headcode":"1U18","dep":578,"arr":577,"days":["MF"]},{"id":"202606197177157","operator":"SN","headcode":"1U18","dep":579,"arr":578,"days":["MF"]},{"id":"202606207126280","operator":"SN","headcode":"1F08","dep":599,"arr":598,"days":["MF"]},{"id":"202606197126279","operator":"SN","headcode":"1F08","dep":599,"arr":598,"days":["MF"]},{"id":"202606198732619","operator":"SN","headcode":"2D22","dep":625,"arr":624,"days":["MF"]},{"id":"202606208727781","operator":"SN","headcode":"2D22","dep":625,"arr":624,"days":["MF"]},{"id":"202606207177162","operator":"SN","headcode":"1U22","dep":637,"arr":636,"days":["MF"]},{"id":"202606197177161","operator":"SN","headcode":"1U22","dep":637,"arr":636,"days":["MF"]},{"id":"202606197126284","operator":"SN","headcode":"1F12","dep":659,"arr":658,"days":["MF"]},{"id":"202606207126285","operator":"SN","headcode":"1F12","dep":660,"arr":658,"days":["MF"]},{"id":"202606198732581","operator":"SN","headcode":"2D26","dep":685,"arr":684,"days":["MF"]},{"id":"202606206756147","operator":"SN","headcode":"2D26","dep":685,"arr":684,"days":["MF"]},{"id":"202606197177165","operator":"SN","headcode":"1U26","dep":696,"arr":696,"days":["MF"]},{"id":"202606207177166","operator":"SN","headcode":"1U26","dep":697,"arr":696,"days":["MF"]},{"id":"202606207126290","operator":"SN","headcode":"1F16","dep":719,"arr":718,"days":["MF"]},{"id":"202606197126289","operator":"SN","headcode":"1F16","dep":719,"arr":718,"days":["MF"]},{"id":"202606198732615","operator":"SN","headcode":"2D30","dep":745,"arr":744,"days":["MF"]},{"id":"202606208727773","operator":"SN","headcode":"2D30","dep":745,"arr":744,"days":["MF"]},{"id":"202606197177169","operator":"SN","headcode":"1U30","dep":756,"arr":756,"days":["MF"]},{"id":"202606207177170","operator":"SN","headcode":"1U30","dep":757,"arr":756,"days":["MF"]},{"id":"202606207126296","operator":"SN","headcode":"1F20","dep":779,"arr":778,"days":["MF"]},{"id":"202606197126295","operator":"SN","headcode":"1F20","dep":779,"arr":778,"days":["MF"]},{"id":"202606198732584","operator":"SN","headcode":"2D34","dep":805,"arr":804,"days":["MF"]},{"id":"202606206722109","operator":"SN","headcode":"2D34","dep":805,"arr":804,"days":["MF"]},{"id":"202606197177173","operator":"SN","headcode":"1U34","dep":816,"arr":816,"days":["MF"]},{"id":"202606207177174","operator":"SN","headcode":"1U34","dep":817,"arr":816,"days":["MF"]},{"id":"202606197126301","operator":"SN","headcode":"1F24","dep":839,"arr":838,"days":["MF"]},{"id":"202606207126302","operator":"SN","headcode":"1F24","dep":840,"arr":838,"days":["MF"]},{"id":"202606198732594","operator":"SN","headcode":"2D38","dep":865,"arr":864,"days":["MF"]},{"id":"202606208727775","operator":"SN","headcode":"2D38","dep":865,"arr":864,"days":["MF"]},{"id":"202606197177177","operator":"SN","headcode":"1U38","dep":876,"arr":876,"days":["MF"]},{"id":"202606207177178","operator":"SN","headcode":"1U38","dep":877,"arr":876,"days":["MF"]},{"id":"202606207126308","operator":"SN","headcode":"1F28","dep":899,"arr":898,"days":["MF"]},{"id":"202606197126307","operator":"SN","headcode":"1F28","dep":899,"arr":898,"days":["MF"]},{"id":"202606198732579","operator":"SN","headcode":"2D42","dep":925,"arr":924,"days":["MF"]},{"id":"202606208727794","operator":"SN","headcode":"2D42","dep":925,"arr":924,"days":["MF"]},{"id":"202606197177181","operator":"SN","headcode":"1U42","dep":936,"arr":935,"days":["MF"]},{"id":"202606207127038","operator":"SN","headcode":"1U42","dep":938,"arr":937,"days":["MF"]},{"id":"202606207126313","operator":"SN","headcode":"1F32","dep":960,"arr":959,"days":["MF"]},{"id":"202606197126372","operator":"SN","headcode":"1F90","dep":961,"arr":960,"days":["MF"]},{"id":"202606198732598","operator":"SN","headcode":"2D46","dep":985,"arr":984,"days":["MF"]},{"id":"202606208727756","operator":"SN","headcode":"2D46","dep":985,"arr":984,"days":["MF"]},{"id":"202606207127040","operator":"SN","headcode":"1U46","dep":998,"arr":997,"days":["MF"]},{"id":"202606197177185","operator":"SN","headcode":"1U46","dep":998,"arr":997,"days":["MF"]},{"id":"202606207126319","operator":"SN","headcode":"1F36","dep":1020,"arr":1019,"days":["MF"]},{"id":"202606197126318","operator":"SN","headcode":"1F36","dep":1020,"arr":1019,"days":["MF"]},{"id":"202606198732629","operator":"SN","headcode":"2D50","dep":1044,"arr":1044,"days":["MF"]},{"id":"202606208727780","operator":"SN","headcode":"2D50","dep":1045,"arr":1044,"days":["MF"]},{"id":"202606207127042","operator":"SN","headcode":"1U50","dep":1058,"arr":1057,"days":["MF"]},{"id":"202606197127041","operator":"SN","headcode":"1U50","dep":1058,"arr":1057,"days":["MF"]},{"id":"202606207126324","operator":"SN","headcode":"1F40","dep":1080,"arr":1079,"days":["MF"]},{"id":"202606197126373","operator":"SN","headcode":"1F92","dep":1082,"arr":1081,"days":["MF"]},{"id":"202606198732576","operator":"SN","headcode":"2D54","dep":1105,"arr":1105,"days":["MF"]},{"id":"202606206722134","operator":"SN","headcode":"2D54","dep":1105,"arr":1104,"days":["MF"]},{"id":"202606207127044","operator":"SN","headcode":"1U54","dep":1118,"arr":1117,"days":["MF"]},{"id":"202606197127043","operator":"SN","headcode":"1U54","dep":1118,"arr":1117,"days":["MF"]},{"id":"202606207126330","operator":"SN","headcode":"1F44","dep":1140,"arr":1139,"days":["MF"]},{"id":"202606197126329","operator":"SN","headcode":"1F44","dep":1141,"arr":1140,"days":["MF"]},{"id":"202606198732610","operator":"SN","headcode":"2D58","dep":1165,"arr":1165,"days":["MF"]},{"id":"202606206722209","operator":"SN","headcode":"2D58","dep":1165,"arr":1164,"days":["MF"]},{"id":"202606207177198","operator":"SN","headcode":"1U58","dep":1177,"arr":1176,"days":["MF"]},{"id":"202606197177197","operator":"SN","headcode":"1U58","dep":1177,"arr":1176,"days":["MF"]},{"id":"202606207126336","operator":"SN","headcode":"1F48","dep":1200,"arr":1198,"days":["MF"]},{"id":"202606197126335","operator":"SN","headcode":"1F48","dep":1201,"arr":1200,"days":["MF"]},{"id":"202606196709824","operator":"SN","headcode":"2D62","dep":1225,"arr":1224,"days":["MF"]},{"id":"202606208727799","operator":"SN","headcode":"2D62","dep":1225,"arr":1224,"days":["MF"]},{"id":"202606207177202","operator":"SN","headcode":"1U62","dep":1237,"arr":1236,"days":["MF"]},{"id":"202606197177201","operator":"SN","headcode":"1U62","dep":1237,"arr":1236,"days":["MF"]},{"id":"202606207126342","operator":"SN","headcode":"1F52","dep":1259,"arr":1258,"days":["MF"]},{"id":"202606197126341","operator":"SN","headcode":"1F52","dep":1260,"arr":1259,"days":["MF"]},{"id":"202606198732624","operator":"SN","headcode":"2D66","dep":1284,"arr":1284,"days":["MF"]},{"id":"202606206756140","operator":"SN","headcode":"2D66","dep":1285,"arr":1284,"days":["MF"]},{"id":"202606197177206","operator":"SN","headcode":"1U66","dep":1296,"arr":1295,"days":["MF"]},{"id":"202606207177207","operator":"SN","headcode":"1U66","dep":1297,"arr":1296,"days":["MF"]},{"id":"202606207126349","operator":"SN","headcode":"1F56","dep":1319,"arr":1318,"days":["MF"]},{"id":"202606197126348","operator":"SN","headcode":"1F56","dep":1319,"arr":1318,"days":["MF"]},{"id":"202606206756174","operator":"SN","headcode":"2D70","dep":1344,"arr":1344,"days":["MF"]},{"id":"202606198732585","operator":"SN","headcode":"2D70","dep":1344,"arr":1344,"days":["MF"]},{"id":"202606207177214","operator":"SN","headcode":"1U70","dep":1356,"arr":1355,"days":["MF"]},{"id":"202606197126354","operator":"SN","headcode":"1F60","dep":1380,"arr":1379,"days":["MF"]},{"id":"202606207177220","operator":"SN","headcode":"1U72","dep":1422,"arr":1421,"days":["MF"]}],"operators":["SN"],"operator_color":"#F0E442","frequency":104},{"next_stop":"STLNRWS","next_stop_name":"St Leonards Warrior Square","destination":"London Victoria","destination_tiploc":"VICTRIC","services":[{"id":"202606198085518","operator":"SE","headcode":"1H58","dep":384,"arr":383,"days":["MF"]},{"id":"202606207126283","operator":"SN","headcode":"1F09","dep":385,"arr":384,"days":["MF"]},{"id":"202606197177138","operator":"SN","headcode":"1U05","dep":397,"arr":395,"days":["MF"]},{"id":"202606207177142","operator":"SN","headcode":"1U07","dep":416,"arr":415,"days":["MF"]},{"id":"202606196709850","operator":"SN","headcode":"2D03","dep":424,"arr":423,"days":["MF"]},{"id":"202606206722237","operator":"SN","headcode":"2D03","dep":432,"arr":432,"days":["MF"]},{"id":"202606197126287","operator":"SN","headcode":"1F13","dep":440,"arr":439,"days":["MF"]},{"id":"202606207126288","operator":"SN","headcode":"1F13","dep":445,"arr":444,"days":["MF"]},{"id":"202606197177143","operator":"SN","headcode":"1U09","dep":456,"arr":455,"days":["MF"]},{"id":"202606207177147","operator":"SN","headcode":"1U11","dep":476,"arr":475,"days":["MF"]},{"id":"202606196709792","operator":"SN","headcode":"2D07","dep":489,"arr":488,"days":["MF"]},{"id":"202606208727798","operator":"SN","headcode":"2D07","dep":491,"arr":491,"days":["MF"]},{"id":"202606207126293","operator":"SN","headcode":"1F17","dep":505,"arr":504,"days":["MF"]},{"id":"202606197126292","operator":"SN","headcode":"1F17","dep":506,"arr":505,"days":["MF"]},{"id":"202606197177150","operator":"SN","headcode":"1U13","dep":520,"arr":519,"days":["MF"]},{"id":"202606207177155","operator":"SN","headcode":"1U15","dep":536,"arr":535,"days":["MF"]},{"id":"202606206756153","operator":"SN","headcode":"2D11","dep":551,"arr":550,"days":["MF"]},{"id":"202606196709817","operator":"SN","headcode":"2D11","dep":553,"arr":552,"days":["MF"]},{"id":"202606197126298","operator":"SN","headcode":"1F21","dep":565,"arr":564,"days":["MF"]},{"id":"202606207126299","operator":"SN","headcode":"1F21","dep":565,"arr":564,"days":["MF"]},{"id":"202606207177160","operator":"SN","headcode":"1U19","dep":596,"arr":595,"days":["MF"]},{"id":"202606197177159","operator":"SN","headcode":"1U19","dep":597,"arr":596,"days":["MF"]},{"id":"202606198729324","operator":"SN","headcode":"2D15","dep":611,"arr":610,"days":["MF"]},{"id":"202606206756142","operator":"SN","headcode":"2D15","dep":611,"arr":610,"days":["MF"]},{"id":"202606197126304","operator":"SN","headcode":"1F25","dep":625,"arr":625,"days":["MF"]},{"id":"202606207126305","operator":"SN","headcode":"1F25","dep":625,"arr":624,"days":["MF"]},{"id":"202606207177164","operator":"SN","headcode":"1U23","dep":656,"arr":655,"days":["MF"]},{"id":"202606197177163","operator":"SN","headcode":"1U23","dep":656,"arr":655,"days":["MF"]},{"id":"202606198732546","operator":"SN","headcode":"2D19","dep":671,"arr":670,"days":["MF"]},{"id":"202606208727795","operator":"SN","headcode":"2D19","dep":671,"arr":670,"days":["MF"]},{"id":"202606197126310","operator":"SN","headcode":"1F29","dep":685,"arr":685,"days":["MF"]},{"id":"202606207126311","operator":"SN","headcode":"1F29","dep":685,"arr":684,"days":["MF"]},{"id":"202606197177167","operator":"SN","headcode":"1U27","dep":716,"arr":715,"days":["MF"]},{"id":"202606207177168","operator":"SN","headcode":"1U27","dep":716,"arr":715,"days":["MF"]},{"id":"202606196709829","operator":"SN","headcode":"2D23","dep":731,"arr":730,"days":["MF"]},{"id":"202606206722128","operator":"SN","headcode":"2D23","dep":731,"arr":730,"days":["MF"]},{"id":"202606197126315","operator":"SN","headcode":"1F33","dep":745,"arr":744,"days":["MF"]},{"id":"202606207126316","operator":"SN","headcode":"1F33","dep":745,"arr":744,"days":["MF"]},{"id":"202606197177171","operator":"SN","headcode":"1U31","dep":776,"arr":775,"days":["MF"]},{"id":"202606207177172","operator":"SN","headcode":"1U31","dep":776,"arr":775,"days":["MF"]},{"id":"202606196709847","operator":"SN","headcode":"2D27","dep":791,"arr":790,"days":["MF"]},{"id":"202606206722214","operator":"SN","headcode":"2D27","dep":791,"arr":790,"days":["MF"]},{"id":"202606197126321","operator":"SN","headcode":"1F37","dep":805,"arr":804,"days":["MF"]},{"id":"202606207126322","operator":"SN","headcode":"1F37","dep":805,"arr":804,"days":["MF"]},{"id":"202606207177176","operator":"SN","headcode":"1U35","dep":836,"arr":835,"days":["MF"]},{"id":"202606197177175","operator":"SN","headcode":"1U35","dep":836,"arr":835,"days":["MF"]},{"id":"202606198729312","operator":"SN","headcode":"2D31","dep":851,"arr":850,"days":["MF"]},{"id":"202606206722140","operator":"SN","headcode":"2D31","dep":851,"arr":850,"days":["MF"]},{"id":"202606197126326","operator":"SN","headcode":"1F41","dep":865,"arr":864,"days":["MF"]},{"id":"202606207126327","operator":"SN","headcode":"1F41","dep":865,"arr":864,"days":["MF"]},{"id":"202606207177180","operator":"SN","headcode":"1U39","dep":895,"arr":894,"days":["MF"]},{"id":"202606197127037","operator":"SN","headcode":"1U39","dep":896,"arr":895,"days":["MF"]},{"id":"202606198729315","operator":"SN","headcode":"2D35","dep":911,"arr":910,"days":["MF"]},{"id":"202606208727772","operator":"SN","headcode":"2D35","dep":911,"arr":910,"days":["MF"]},{"id":"202606197126332","operator":"SN","headcode":"1F45","dep":925,"arr":924,"days":["MF"]},{"id":"202606207126333","operator":"SN","headcode":"1F45","dep":925,"arr":924,"days":["MF"]},{"id":"202606207177184","operator":"SN","headcode":"1U43","dep":955,"arr":954,"days":["MF"]},{"id":"202606197127039","operator":"SN","headcode":"1U43","dep":956,"arr":955,"days":["MF"]},{"id":"202606198732582","operator":"SN","headcode":"2D39","dep":971,"arr":970,"days":["MF"]},{"id":"202606208727779","operator":"SN","headcode":"2D39","dep":971,"arr":970,"days":["MF"]},{"id":"202606197126338","operator":"SN","headcode":"1F49","dep":985,"arr":984,"days":["MF"]},{"id":"202606207126339","operator":"SN","headcode":"1F49","dep":985,"arr":984,"days":["MF"]},{"id":"202606207177188","operator":"SN","headcode":"1U47","dep":1015,"arr":1014,"days":["MF"]},{"id":"202606197177187","operator":"SN","headcode":"1U47","dep":1016,"arr":1015,"days":["MF"]},{"id":"202606198732652","operator":"SN","headcode":"2D43","dep":1031,"arr":1030,"days":["MF"]},{"id":"202606206722205","operator":"SN","headcode":"2D43","dep":1031,"arr":1030,"days":["MF"]},{"id":"202606197126344","operator":"SN","headcode":"1F53","dep":1045,"arr":1044,"days":["MF"]},{"id":"202606207126345","operator":"SN","headcode":"1F53","dep":1045,"arr":1044,"days":["MF"]},{"id":"202606207177192","operator":"SN","headcode":"1U51","dep":1075,"arr":1074,"days":["MF"]},{"id":"202606197177191","operator":"SN","headcode":"1U51","dep":1076,"arr":1075,"days":["MF"]},{"id":"202606208727783","operator":"SN","headcode":"2D47","dep":1091,"arr":1090,"days":["MF"]},{"id":"202606198729305","operator":"SN","headcode":"2D47","dep":1093,"arr":1092,"days":["MF"]},{"id":"202606197126351","operator":"SN","headcode":"1F57","dep":1105,"arr":1105,"days":["MF"]},{"id":"202606207126352","operator":"SN","headcode":"1F57","dep":1105,"arr":1104,"days":["MF"]},{"id":"202606207177196","operator":"SN","headcode":"1U55","dep":1135,"arr":1134,"days":["MF"]},{"id":"202606197177195","operator":"SN","headcode":"1U55","dep":1136,"arr":1135,"days":["MF"]},{"id":"202606198732605","operator":"SN","headcode":"2D51","dep":1151,"arr":1150,"days":["MF"]},{"id":"202606208727770","operator":"SN","headcode":"2D51","dep":1151,"arr":1150,"days":["MF"]},{"id":"202606197126357","operator":"SN","headcode":"1F61","dep":1165,"arr":1164,"days":["MF"]},{"id":"202606207126358","operator":"SN","headcode":"1F61","dep":1165,"arr":1164,"days":["MF"]},{"id":"202606207177200","operator":"SN","headcode":"1U59","dep":1196,"arr":1195,"days":["MF"]},{"id":"202606197177199","operator":"SN","headcode":"1U59","dep":1199,"arr":1198,"days":["MF"]},{"id":"202606196709836","operator":"SN","headcode":"2D55","dep":1211,"arr":1210,"days":["MF"]},{"id":"202606208727789","operator":"SN","headcode":"2D55","dep":1211,"arr":1210,"days":["MF"]},{"id":"202606207126364","operator":"SN","headcode":"1F65","dep":1225,"arr":1224,"days":["MF"]},{"id":"202606197126363","operator":"SN","headcode":"1F65","dep":1225,"arr":1224,"days":["MF"]},{"id":"202606197177204","operator":"SN","headcode":"1U63","dep":1256,"arr":1255,"days":["MF"]},{"id":"202606207177205","operator":"SN","headcode":"1U63","dep":1256,"arr":1255,"days":["MF"]},{"id":"202606198732609","operator":"SN","headcode":"2D59","dep":1271,"arr":1270,"days":["MF"]},{"id":"202606208727763","operator":"SN","headcode":"2D59","dep":1271,"arr":1270,"days":["MF"]},{"id":"202606197126370","operator":"SN","headcode":"1F69","dep":1285,"arr":1284,"days":["MF"]},{"id":"202606207126371","operator":"SN","headcode":"1F69","dep":1285,"arr":1284,"days":["MF"]},{"id":"202606197177210","operator":"SN","headcode":"1U67","dep":1316,"arr":1315,"days":["MF"]},{"id":"202606207177211","operator":"SN","headcode":"1U67","dep":1316,"arr":1315,"days":["MF"]},{"id":"202606198732620","operator":"SN","headcode":"2D63","dep":1331,"arr":1330,"days":["MF"]},{"id":"202606206722146","operator":"SN","headcode":"2D63","dep":1331,"arr":1330,"days":["MF"]},{"id":"202606197127048","operator":"SN","headcode":"1U71","dep":1351,"arr":1350,"days":["MF"]},{"id":"202606207127049","operator":"SN","headcode":"1U71","dep":1356,"arr":1355,"days":["MF"]},{"id":"202606208727774","operator":"SN","headcode":"2D67","dep":1391,"arr":1391,"days":["MF"]},{"id":"202606197127051","operator":"SN","headcode":"1U73","dep":1410,"arr":1409,"days":["MF"]},{"id":"202606207127053","operator":"SN","headcode":"1U75","dep":1410,"arr":1409,"days":["MF"]}],"operators":["SE","SN"],"operator_color":"#F0E442","frequency":101},{"next_stop":null,"next_stop_name":"Hastings","destination":"Hastings","destination_tiploc":"HASTING","services":[{"id":"202606196722317","operator":"SN","headcode":"2D67","dep":null,"arr":1394,"days":["MF"]},{"id":"202606196722320","operator":"SN","headcode":"2D69","dep":null,"arr":9,"days":["MF"]},{"id":"202606208727762","operator":"SN","headcode":"2D69","dep":null,"arr":11,"days":["MF"]}],"operators":["SN"],"operator_color":"#F0E442","frequency":3}]}