{"station":"ULESKLF","station_name":"Ulleskelf","n_services":38,"branches":[{"next_stop":"ULESKLF","next_stop_name":"Ulleskelf","destination":"Leeds","destination_tiploc":"LEEDS","services":[{"id":"202606207840062","operator":"NT","headcode":"0B00","dep":329,"arr":null,"days":["MF"]},{"id":"202606198024403","operator":"NT","headcode":"2R01","dep":376,"arr":null,"days":["MF"]},{"id":"202606207845782","operator":"NT","headcode":"0B00","dep":413,"arr":null,"days":["MF"]},{"id":"202606197188958","operator":"NT","headcode":"1B17","dep":431,"arr":null,"days":["MF"]},{"id":"202606206732956","operator":"NT","headcode":"2R03","dep":445,"arr":null,"days":["MF"]},{"id":"202606196732956","operator":"NT","headcode":"2R03","dep":446,"arr":null,"days":["MF"]},{"id":"202606198028496","operator":"NT","headcode":"2T93","dep":466,"arr":null,"days":["MF"]},{"id":"202606207845766","operator":"NT","headcode":"0B00","dep":473,"arr":null,"days":["MF"]},{"id":"202606196708891","operator":"NT","headcode":"2Y87","dep":539,"arr":null,"days":["MF"]},{"id":"202606206733309","operator":"NT","headcode":"2Y87","dep":547,"arr":null,"days":["MF"]},{"id":"202606208028850","operator":"NT","headcode":"2Y89","dep":791,"arr":null,"days":["MF"]},{"id":"202606198028849","operator":"NT","headcode":"2Y89","dep":791,"arr":null,"days":["MF"]},{"id":"202606208024471","operator":"NT","headcode":"2R21","dep":939,"arr":null,"days":["MF"]},{"id":"202606198024471","operator":"NT","headcode":"2R21","dep":941,"arr":null,"days":["MF"]},{"id":"202606208028854","operator":"NT","headcode":"2Y91","dep":1018,"arr":null,"days":["MF"]},{"id":"202606198028853","operator":"NT","headcode":"2Y91","dep":1018,"arr":null,"days":["MF"]},{"id":"202606207845771","operator":"NT","headcode":"0B00","dep":1073,"arr":null,"days":["MF"]},{"id":"202606198028497","operator":"NT","headcode":"2T94","dep":1089,"arr":null,"days":["MF"]},{"id":"202606208024518","operator":"NT","headcode":"2R35","dep":1365,"arr":null,"days":["MF"]},{"id":"202606198024517","operator":"NT","headcode":"2R35","dep":1367,"arr":null,"days":["MF"]}],"operators":["NT"],"operator_color":"#0072B2","frequency":20},{"next_stop":null,"next_stop_name":"York","destination":"York","destination_tiploc":"YORK","services":[{"id":"202606198024419","operator":"NT","headcode":"2R04","dep":null,"arr":656,"days":["MF"]},{"id":"202606208024419","operator":"NT","headcode":"2R04","dep":null,"arr":656,"days":["MF"]},{"id":"202606198024540","operator":"NT","headcode":"2R50","dep":null,"arr":512,"days":["MF"]},{"id":"202606208024540","operator":"NT","headcode":"2R50","dep":null,"arr":512,"days":["MF"]},{"id":"202606198028841","operator":"NT","headcode":"2Y70","dep":null,"arr":529,"days":["MF"]},{"id":"202606208028841","operator":"NT","headcode":"2Y70","dep":null,"arr":532,"days":["MF"]},{"id":"202606208028843","operator":"NT","headcode":"2Y74","dep":null,"arr":778,"days":["MF"]},{"id":"202606208028846","operator":"NT","headcode":"2Y76","dep":null,"arr":1014,"days":["MF"]},{"id":"202606196708791","operator":"NT","headcode":"2T92","dep":null,"arr":1101,"days":["MF"]},{"id":"202606198028437","operator":"NT","headcode":"2T33","dep":null,"arr":1316,"days":["MF"]},{"id":"202606198028845","operator":"NT","headcode":"2Y76","dep":null,"arr":1013,"days":["MF"]},{"id":"202606198024449","operator":"NT","headcode":"2R14","dep":null,"arr":961,"days":["MF"]},{"id":"202606196733308","operator":"NT","headcode":"2Y74","dep":null,"arr":778,"days":["MF"]},{"id":"202606208024449","operator":"NT","headcode":"2R14","dep":null,"arr":961,"days":["MF"]},{"id":"202606207845695","operator":"NT","headcode":"0B00","dep":null,"arr":1399,"days":["MF"]},{"id":"202606207845696","operator":"NT","headcode":"0B00","dep":null,"arr":1159,"days":["MF"]},{"id":"202606208024523","operator":"NT","headcode":"2R38","dep":null,"arr":451,"days":["MF"]},{"id":"202606198024523","operator":"NT","headcode":"2R38","dep":null,"arr":451,"days":["MF"]}],"operators":["NT"],"operator_color":"#0072B2","frequency":18}]}